s3streaming/__init__.py
s3streaming/opener.py
s3streaming/stream.py
tests/__init__.py
s3_streaming-0.0.3.dist-info/LICENSE
s3_streaming-0.0.3.dist-info/METADATA
s3_streaming-0.0.3.dist-info/WHEEL
s3_streaming-0.0.3.dist-info/top_level.txt
s3_streaming-0.0.3.dist-info/RECORD
