Metadata-Version: 2.1
Name: s3-streaming
Version: 0.0.3
Summary: stream and (de)serialize s3 objects with no local footprint
Home-page: https://github.com/robhowley/s3-streaming
Author: Rob Howley
Author-email: howley.robert@gmail.com
License: UNKNOWN
Platform: UNKNOWN
Classifier: Programming Language :: Python :: 3
Classifier: License :: OSI Approved :: MIT License
Classifier: Operating System :: OS Independent
